
{"d":"[{\"GLAcct\":\"905.03\",\"Borough\":\"2\",\"GLDescription\":\"WO-UTL- BRONX\",\"BeginBalance\":\"-$22,818.96\",\"TodaysDebits\":\"$0.00\",\"TodaysCredits\":\"$0.00\",\"CurrentBalance\":\"-$22,818.96\",\"DateLastTran\":\"01/21/2016\",\"RowCount\":\"422\"},{\"GLAcct\":\"905.03\",\"Borough\":\"3\",\"GLDescription\":\"WO-UTL- BROOKLYN\",\"BeginBalance\":\"-$9,805.04\",\"TodaysDebits\":\"$0.00\",\"TodaysCredits\":\"$0.00\",\"CurrentBalance\":\"-$9,805.04\",\"DateLastTran\":\"02/05/2016\",\"RowCount\":\"423\"},{\"GLAcct\":\"905.03\",\"Borough\":\"4\",\"GLDescription\":\"WO-UTL- QUEENS\",\"BeginBalance\":\"-$121,727.47\",\"TodaysDebits\":\"$0.00\",\"TodaysCredits\":\"$0.00\",\"CurrentBalance\":\"-$121,727.47\",\"DateLastTran\":\"02/05/2016\",\"RowCount\":\"424\"},{\"GLAcct\":\"905.03\",\"Borough\":\"5\",\"GLDescription\":\"WO-UTL- STATEN ISLAND\",\"BeginBalance\":\"-$12,295.23\",\"TodaysDebits\":\"$0.00\",\"TodaysCredits\":\"$0.00\",\"CurrentBalance\":\"-$12,295.23\",\"DateLastTran\":\"01/21/2016\",\"RowCount\":\"425\"},{\"GLAcct\":\"905.14\",\"Borough\":\"1\",\"GLDescription\":\"WO-PLP- MANHATTAN\",\"BeginBalance\":\"$25,623.55\",\"TodaysDebits\":\"$0.00\",\"TodaysCredits\":\"$0.00\",\"CurrentBalance\":\"$25,623.55\",\"DateLastTran\":\"08/31/2009\",\"RowCount\":\"426\"},{\"GLAcct\":\"905.14\",\"Borough\":\"2\",\"GLDescription\":\"WO-PLP- BRONX\",\"BeginBalance\":\"$18,409.23\",\"TodaysDebits\":\"$0.00\",\"TodaysCredits\":\"$0.00\",\"CurrentBalance\":\"$18,409.23\",\"DateLastTran\":\"08/23/2011\",\"RowCount\":\"427\"},{\"GLAcct\":\"905.14\",\"Borough\":\"3\",\"GLDescription\":\"WO-PLP- BROOKLYN\",\"BeginBalance\":\"$11,914.06\",\"TodaysDebits\":\"$0.00\",\"TodaysCredits\":\"$0.00\",\"CurrentBalance\":\"$11,914.06\",\"DateLastTran\":\"06/29/2010\",\"RowCount\":\"428\"},{\"GLAcct\":\"905.14\",\"Borough\":\"4\",\"GLDescription\":\"WO-PLP- QUEENS\",\"BeginBalance\":\"$23,825.78\",\"TodaysDebits\":\"$0.00\",\"TodaysCredits\":\"$0.00\",\"CurrentBalance\":\"$23,825.78\",\"DateLastTran\":\"07/20/2010\",\"RowCount\":\"429\"},{\"GLAcct\":\"905.14\",\"Borough\":\"5\",\"GLDescription\":\"WO-PLP- STATEN ISLAND\",\"BeginBalance\":\"$6,622.14\",\"TodaysDebits\":\"$0.00\",\"TodaysCredits\":\"$0.00\",\"CurrentBalance\":\"$6,622.14\",\"DateLastTran\":\"06/22/2010\",\"RowCount\":\"430\"},{\"GLAcct\":\"905.15\",\"Borough\":\"2\",\"GLDescription\":\"WO-PUT- BRONX\",\"BeginBalance\":\"$40,164.46\",\"TodaysDebits\":\"$0.00\",\"TodaysCredits\":\"$0.00\",\"CurrentBalance\":\"$40,164.46\",\"DateLastTran\":\"11/03/2010\",\"RowCount\":\"431\"},{\"GLAcct\":\"905.15\",\"Borough\":\"3\",\"GLDescription\":\"WO-PUT- BROOKLYN\",\"BeginBalance\":\"$15,481.26\",\"TodaysDebits\":\"$0.00\",\"TodaysCredits\":\"$0.00\",\"CurrentBalance\":\"$15,481.26\",\"DateLastTran\":\"08/07/2014\",\"RowCount\":\"432\"},{\"GLAcct\":\"905.15\",\"Borough\":\"4\",\"GLDescription\":\"WO-PUT- QUEENS\",\"BeginBalance\":\"$8,707.80\",\"TodaysDebits\":\"$0.00\",\"TodaysCredits\":\"$0.00\",\"CurrentBalance\":\"$8,707.80\",\"DateLastTran\":\"11/14/2012\",\"RowCount\":\"433\"},{\"GLAcct\":\"905.15\",\"Borough\":\"5\",\"GLDescription\":\"WO-PUT- STATEN ISLAND\",\"BeginBalance\":\"$5,418.21\",\"TodaysDebits\":\"$0.00\",\"TodaysCredits\":\"$0.00\",\"CurrentBalance\":\"$5,418.21\",\"DateLastTran\":\"06/22/2010\",\"RowCount\":\"434\"}]"}